docdbdemo/__init__.py
docdbdemo/py.typed
docdbdemo/_jsii/__init__.py
docdbdemo/_jsii/doc_db_lib@0.1.0-alpha.6.jsii.tgz
docdbdemo-0.1.0a6.dist-info/METADATA
docdbdemo-0.1.0a6.dist-info/WHEEL
docdbdemo-0.1.0a6.dist-info/top_level.txt
docdbdemo-0.1.0a6.dist-info/RECORD
